src/KeyPressesSender.py
src/LICENSE
src/MainDialog.py
src/UI.py
src/__init__.py
src/keys.txt
src/qaffeine.py
src/res/icon_black_off.png
src/res/icon_black_on.png
src/res/icon_color.png
src/res/icon_white_off.png
src/res/icon_white_on.png
src/res/maindialog.ui
qaffeine-0.1.post2.dist-info/METADATA
qaffeine-0.1.post2.dist-info/WHEEL
qaffeine-0.1.post2.dist-info/entry_points.txt
qaffeine-0.1.post2.dist-info/top_level.txt
qaffeine-0.1.post2.dist-info/RECORD
