Metadata-Version: 2.1
Name: qaffeine
Version: 0.1.post2
Summary: Prevent your computer from entering inactivity modes
Home-page: https://github.com/clorteau/qaffeine
Author: Clem Lorteau
Author-email: clem@lorteau.fr
License: Unlicense
Platform: UNKNOWN
Classifier: Programming Language :: Python :: 3
Classifier: License :: Public Domain
Classifier: Operating System :: OS Independent
Requires-Python: >=3
Requires-Dist: PySide2
Requires-Dist: autogui
